datalayer_ui/__init__.py
datalayer_ui/__main__.py
datalayer_ui/_version.py
datalayer_ui/lab.py
datalayer_ui/serverapplication.py
datalayer_ui/handlers/__init__.py
datalayer_ui/handlers/base.py
datalayer_ui/handlers/index/__init__.py
datalayer_ui/handlers/index/handler.py
datalayer_ui/handlers/resource_usage/__init__.py
datalayer_ui/handlers/resource_usage/api_handler.py
datalayer_ui/handlers/resource_usage/config.py
datalayer_ui/handlers/resource_usage/metrics.py
datalayer_ui/handlers/resource_usage/prometheus.py
datalayer_ui/handlers/resource_usage/runtime_handler.py
datalayer_ui/handlers/resource_usage/utils.py
datalayer_ui/labextension/static/lite-service-worker.js
datalayer_ui/static/1009.datalayer-ui.js
datalayer_ui/static/107.datalayer-ui.js
datalayer_ui/static/1070.datalayer-ui.js
datalayer_ui/static/1159.datalayer-ui.js
datalayer_ui/static/1162.datalayer-ui.js
datalayer_ui/static/1195.datalayer-ui.js
datalayer_ui/static/1234.datalayer-ui.js
datalayer_ui/static/1239.datalayer-ui.js
datalayer_ui/static/1264.datalayer-ui.js
datalayer_ui/static/1271.datalayer-ui.js
datalayer_ui/static/1290.datalayer-ui.js
datalayer_ui/static/1307.datalayer-ui.js
datalayer_ui/static/1367.datalayer-ui.js
datalayer_ui/static/1376.datalayer-ui.js
datalayer_ui/static/1547.datalayer-ui.js
datalayer_ui/static/157.datalayer-ui.js
datalayer_ui/static/1576.datalayer-ui.js
datalayer_ui/static/1587.datalayer-ui.js
datalayer_ui/static/1617.datalayer-ui.js
datalayer_ui/static/1648.datalayer-ui.js
datalayer_ui/static/1653.datalayer-ui.js
datalayer_ui/static/1671.datalayer-ui.js
datalayer_ui/static/1693.datalayer-ui.js
datalayer_ui/static/1714.datalayer-ui.js
datalayer_ui/static/1736.datalayer-ui.js
datalayer_ui/static/179.datalayer-ui.js
datalayer_ui/static/1830.datalayer-ui.js
datalayer_ui/static/1871.datalayer-ui.js
datalayer_ui/static/1893.datalayer-ui.js
datalayer_ui/static/1902.datalayer-ui.js
datalayer_ui/static/1904.datalayer-ui.js
datalayer_ui/static/197.datalayer-ui.js
datalayer_ui-1.0.25.dist-info/METADATA
datalayer_ui-1.0.25.dist-info/WHEEL
datalayer_ui-1.0.25.dist-info/entry_points.txt
datalayer_ui-1.0.25.dist-info/licenses/LICENSE
datalayer_ui-1.0.25.dist-info/RECORD
