Metadata-Version: 2.1
Name: datalayer_ui
Version: 1.0.25
Summary: Datalayer User Interface
Project-URL: Homepage, https://github.com/datalayer
Project-URL: Bug Tracker, https://github.com/datalayer/support/issues
Author-email: Datalayer <info@datalayer.io>
License: Datalayer License
License-File: LICENSE
Classifier: Framework :: Jupyter
Classifier: Framework :: Jupyter :: JupyterLab
Classifier: Framework :: Jupyter :: JupyterLab :: 4
Classifier: Framework :: Jupyter :: JupyterLab :: Extensions
Classifier: Framework :: Jupyter :: JupyterLab :: Extensions :: Prebuilt
Classifier: Intended Audience :: Developers
Classifier: Intended Audience :: Science/Research
Classifier: Intended Audience :: System Administrators
Classifier: Programming Language :: Python
Classifier: Programming Language :: Python :: 3
Classifier: Programming Language :: Python :: 3.9
Classifier: Programming Language :: Python :: 3.10
Classifier: Programming Language :: Python :: 3.11
Requires-Python: >=3.9
Requires-Dist: jupyter-server<3,>=2.10
Requires-Dist: traitlets
Provides-Extra: test
Requires-Dist: coverage; extra == 'test'
Requires-Dist: pytest; extra == 'test'
Requires-Dist: pytest-asyncio; extra == 'test'
Requires-Dist: pytest-cov; extra == 'test'
Requires-Dist: pytest-jupyter; extra == 'test'
Requires-Dist: pytest-tornasync; extra == 'test'
